__init__.py
camera/__init__.py
camera/camera_status.py
endustry/__init__.py
endustry/atomic_capability.py
endustry/edge_post.py
tools/__init__.py
tools/general_tools.py
tools/ss_tools.py
endustry-0.0.6.dist-info/LICENSE
endustry-0.0.6.dist-info/METADATA
endustry-0.0.6.dist-info/WHEEL
endustry-0.0.6.dist-info/top_level.txt
endustry-0.0.6.dist-info/RECORD
