Metadata-Version: 2.1
Name: endustry
Version: 0.0.6
Summary: A small pakage for api call on Huawei EI platform
Author-email: linweicheng <linweicheng24@gmail.com>
Project-URL: preson blog, http://op.wwooww.com:35600
Project-URL: Homepage, https://github.com/pypa/sampleproject
Project-URL: Bug Tracker, https://github.com/pypa/sampleproject/issues
Classifier: Programming Language :: Python :: 3
Classifier: License :: OSI Approved :: MIT License
Classifier: Operating System :: OS Independent
Requires-Python: >=3.7
License-File: LICENSE
